{
  "best_epoch": 5,
  "peak_cpu_memory_MB": 4719.364,
  "peak_gpu_0_memory_MB": 3,
  "peak_gpu_1_memory_MB": 3,
  "peak_gpu_2_memory_MB": 3,
  "peak_gpu_3_memory_MB": 3,
  "peak_gpu_4_memory_MB": 17672,
  "peak_gpu_5_memory_MB": 3,
  "peak_gpu_6_memory_MB": 3,
  "peak_gpu_7_memory_MB": 3,
  "training_duration": "0:33:34.876080",
  "training_start_epoch": 0,
  "training_epochs": 5,
  "epoch": 5,
  "training_acc": 0,
  "training_no_result": 0,
  "training_loss": 0.8448473995382135,
  "training_cpu_memory_MB": 4719.364,
  "training_gpu_0_memory_MB": 3,
  "training_gpu_1_memory_MB": 3,
  "training_gpu_2_memory_MB": 3,
  "training_gpu_3_memory_MB": 3,
  "training_gpu_4_memory_MB": 17672,
  "training_gpu_5_memory_MB": 3,
  "training_gpu_6_memory_MB": 3,
  "training_gpu_7_memory_MB": 3,
  "validation_BLEU": 0.3522097889512166,
  "validation_acc": 0.44285300925925924,
  "validation_no_result": 0.13151041666666666,
  "validation_loss": 0.8661380161841711,
  "best_validation_BLEU": 0.3522097889512166,
  "best_validation_acc": 0.44285300925925924,
  "best_validation_no_result": 0.13151041666666666,
  "best_validation_loss": 0.8661380161841711
}